flexible_list_of_values/__init__.py
flexible_list_of_values/admin.py
flexible_list_of_values/apps.py
flexible_list_of_values/exceptions.py
flexible_list_of_values/forms.py
flexible_list_of_values/management/__init__.py
flexible_list_of_values/management/commands/__init__.py
flexible_list_of_values/management/commands/update_lovs.py
flexible_list_of_values/migrations/__init__.py
flexible_list_of_values/models.py
flexible_list_of_values/urls.py
flexible_list_of_values/views.py
flexible_list_of_values-0.2.0.dist-info/LICENSE
flexible_list_of_values-0.2.0.dist-info/WHEEL
flexible_list_of_values-0.2.0.dist-info/METADATA
flexible_list_of_values-0.2.0.dist-info/RECORD
