Metadata-Version: 2.1
Name: flexible-list-of-values
Version: 0.2.0
Summary: Flexible Lists of Values (LOV) for Django
Home-page: https://github.com/jacklinke/flexible-list-of-values
License: MIT
Keywords: django
Author: Jack Linke
Author-email: jack@watervize.com
Requires-Python: >=3.8,<4.0
Classifier: Development Status :: 3 - Alpha
Classifier: Environment :: Web Environment
Classifier: Framework :: Django
Classifier: Framework :: Django :: 3.2
Classifier: Framework :: Django :: 4
Classifier: Framework :: Django :: 4.0
Classifier: Framework :: Django :: 4.1
Classifier: Intended Audience :: Developers
Classifier: License :: OSI Approved :: MIT License
Classifier: Programming Language :: Python :: 3
Classifier: Programming Language :: Python :: 3.8
Classifier: Programming Language :: Python :: 3.9
Classifier: Programming Language :: Python :: 3.10
Classifier: Programming Language :: Python :: 3.11
Classifier: Programming Language :: Python :: 3
Classifier: Programming Language :: Python :: 3 :: Only
Requires-Dist: django (>=3.2)
Project-URL: Repository, https://github.com/jacklinke/flexible-list-of-values
